mimicker/__init__.py
mimicker/exceptions.py
mimicker/handler.py
mimicker/logger.py
mimicker/mimicker.py
mimicker/regex.py
mimicker/route.py
mimicker/server.py
mimicker/stub_group.py
mimicker-2.1.2.dist-info/LICENSE
mimicker-2.1.2.dist-info/METADATA
mimicker-2.1.2.dist-info/WHEEL
mimicker-2.1.2.dist-info/RECORD
