Metadata-Version: 2.3
Name: mimicker
Version: 2.1.2
Summary: A lightweight HTTP mocking server for Python
License: MIT
Keywords: http,mocking,testing,mock-server,stubbing,ci-cd,http-server,testing-tools,stub-server,purepython
Author: Amazia Gur
Author-email: amaziagur@gmail.com
Requires-Python: >=3.7,<4.0
Classifier: License :: OSI Approved :: MIT License
Classifier: Programming Language :: Python :: 3
Classifier: Programming Language :: Python :: 3.7
Classifier: Programming Language :: Python :: 3.8
Classifier: Programming Language :: Python :: 3.9
Classifier: Programming Language :: Python :: 3.10
Classifier: Programming Language :: Python :: 3.11
Classifier: Programming Language :: Python :: 3.12
Classifier: Programming Language :: Python :: 3.13
Requires-Dist: colorlog (>=6.9.0,<7.0.0)
Project-URL: Homepage, https://github.com/amaziahub/mimicker
Project-URL: Repository, https://github.com/amaziahub/mimicker
